{
  "articles": [
    {
      "id": "asking-for-referrals-2026",
      "title": "Stop Asking for Referrals at the Ugliest Possible Moment",
      "excerpt": "Most business owners know just how valuable referrals are. Yet surprisingly few have a working system for consistently getting them.",
      "category": "Systems",
      "date": "2026-07-07",
      "image": "",
      "content": "Stop asking for referrals at the ugliest possible moment. It's crippling your response rate.\n\nMost business owners know just how valuable referrals are. Yet surprisingly few have a working system for consistently getting them. So, they ask whenever they happen to remember: at the checkout counter, at the end of a project, or three days later in a follow-up email. Sometimes they don't ask at all because it feels awkward. Talk about leaving money on the table.\n\nHere's the problem: if you're confused about how to ask for referrals, or you're asking but not getting great results, it's because it's not about how to ask but rather when to ask. The right moment to ask for referrals is short and dynamic but by the end of this article, you'll learn to easily identify it and integrate that moment into your system so that you stop asking at ugly moments that cripple your response rate.\n\nThere's only one of you. Entrepreneur Alex Hormozi puts it simply: 'There are two ways people can find out about your stuff. One, you can tell them. Two, other people can tell them. And there's only one of you.'\n\nSimple idea, but it highlights an important reality. You can only reach so many people yourself. Referrals multiply your reach because your happy customers become an extension of your marketing. Instead of one person spreading the word, you suddenly have dozens or eventually hundreds or even thousands of people doing it for you... For bonuses or... drumroll... for FREE.\n\nYou could incentivize referrals by offering bonuses, discounts, etc. Example (Software): Invite a friend. Your friend gets 30% off their first 3 months, and you receive one free month added to your subscription for every friend who becomes a paying customer. Example (Online Coaching Program): Know someone who wants to grow their business? Refer them to our coaching program. If they enroll, they receive our $197 Sales Script Pack for free, and you receive a private 1-hour strategy session (worth $300). You get the idea.\n\nHowever, in this article, our focus is on getting referrals for FREE without offering any bonus, discount, or incentive and still achieving phenomenal results. So it's all about identifying that brief but powerful moment we're about to break down.\n\nThink about the last time you watched an incredible movie. The moment you walked out of the cinema, you probably couldn't wait to tell someone about it. You were excited. The emotions were fresh. Now imagine someone asks you six weeks later. You may still recommend it but the excitement has faded. You're far less enthusiastic than you were immediately after watching it. Customers behave the same way. The emotional peak doesn't last forever, and once it's gone, you've missed your best opportunity.\n\nThe window you're overlooking. Pay attention to the moments your customers say something positive without you asking. Maybe they send you a message saying: 'This is amazing.' 'This solved my problem.' 'Thank you so much.' 'I'm really impressed.' Those comments are more valuable than you realize. Most business owners only see them as testimonials (which are very important, yes). But they also signal that your customer is experiencing peak satisfaction right now.\n\nThat's your window! Not at checkout because it's part of your routine. Not in a generic follow-up email three days later. Not after the excitement has cooled off. Right then! Because in that moment, recommending you to someone else feels natural instead of forced.\n\nNothing complicated. A simple response is often enough: 'I'm really glad it's working for you. Do you know one or two people who'd find this useful as well?' Notice how different that feels from randomly asking everyone for referrals? You're responding to genuine enthusiasm instead of trying to create it.\n\nHammer it into your system. Create a simple rule: Whenever a customer gives unsolicited positive feedback, ask for a referral. Every single time. No guessing. No relying on memory. No wondering whether this customer might be annoyed. You've created a trigger. Just like your business has a system for sending invoices or following up with leads, build this system for free referrals. Once the trigger exists, consistency becomes automatic. And consistency is what produces results.\n\nWhy this compounds. Imagine you have 100 satisfied customers. If each of them referred just two friends over time, that's 200 potential new customers without spending additional money on advertising. Of course, not every referral will become a customer. Not every customer will refer exactly two people either. The point isn't the exact number it's the multiplication effect. Every satisfied customer has the potential to introduce your business to people who already trust the recommendation because it came from someone they know.\n\nThat's one reason referrals are often among the highest-quality leads a business can receive- they arrive with a level of trust that's difficult to create through advertising alone. Research has consistently found that referred customers tend to convert at higher rates and often deliver greater long-term value than customers acquired through many other channels. Nielsen has repeatedly found that recommendations from people we know are among the most trusted forms of advertising, while research from the Wharton School of the University of Pennsylvania has shown that referred customers can provide greater long-term value than non-referred customers. That's leverage baby!\n\nKey takeaway: People are most willing to recommend you when they're already feeling the value you've created. So don't wait until the moment has passed. Build a simple system: Every time a customer gives you genuine, unsolicited positive feedback, let that become your trigger to ask.\n\nNeed help applying this to your business? Book a free Business Systems Audit with Vantage Solutions. We'll identify your biggest growth bottleneck and give you practical next steps-whether you work with us or not. Send us a DM on any of the platforms below to get started."
    },
    {
      "id": "audience-to-income-2026",
      "title": "Turning an Audience Into Actual Income",
      "excerpt": "Most creators sit on an audience they never monetize. Here's the framework we use to fix that.",
      "category": "Growth",
      "date": "2026-06-20",
      "image": "",
      "content": "Most niche creators have the hardest part done already — they have people paying attention. What's missing is almost never reach, it's an offer and a system to deliver it.\n\nWe start every engagement the same way: audit what the audience already responds to, then build the smallest possible offer that solves one real problem for them.\n\nFrom there it's repetition. Outreach, content, and the systems behind both, run consistently until the offer finds its footing.",
      "link": {
        "url": "https://example.com/blog/audience-to-income",
        "label": "Read the Full Breakdown"
      }
    },
    {
      "id": "free-tools-philosophy",
      "title": "Why We Give Some of This Away for Free",
      "excerpt": "MidMan Pulse is free and always will be. Here's the reasoning, not just the marketing line.",
      "category": "Behind the Scenes",
      "date": "2026-06-10",
      "image": "",
      "content": "Free tools aren't a funnel trick for us, they're a filter. The people who get real value from a free tool are exactly the people worth working with directly.\n\nIt also keeps us honest — a tool has to be good enough to stand on its own with zero pressure to buy anything."
    },
    {
      "id": "content-systems-not-hacks",
      "title": "Content Systems Beat Content Hacks",
      "excerpt": "Growth hacks expire. Systems compound. A short case for building the boring thing first.",
      "category": "Case Study",
      "date": "2026-05-28",
      "image": "",
      "content": "Every few months a new posting trick makes the rounds, gets copied into the ground, and stops working. Meanwhile the accounts that keep growing are running unglamorous systems: a content calendar, a repeatable format, a feedback loop.\n\nWe'd rather hand a client a system they can run without us in six months than a hack that dies in six weeks.",
      "link": {
        "url": "https://example.com/blog/content-systems",
        "label": "See the Full Case Study"
      }
    }
  ]
}
